udbworker/__init__.py
udbworker/errors.py
udbworker/types.py
udbworker-0.4.1.dist-info/LICENSE
udbworker-0.4.1.dist-info/METADATA
udbworker-0.4.1.dist-info/WHEEL
udbworker-0.4.1.dist-info/top_level.txt
udbworker-0.4.1.dist-info/RECORD
