Metadata-Version: 2.1
Name: udbworker
Version: 0.4.1
Summary: (not)Universal Database Worker
Home-page: UNKNOWN
Author-email: E2r7hN07Fl47@protonmail.com
License: UNKNOWN
Platform: UNKNOWN
License-File: LICENSE
